{
  "pcm": {
    "title":  "Ma super pcm !!",
    "description": "Ici une super description expliquant ma PCM !!!!",
    "invert": "false",
    "style": {
      "color": "#000000",
      "backgroundColor": "#ffffff"
    },
    "operations": [
      {
        "type": "comparison",
        "values": {
          "operation": "<",
          "operand": "200"
        },
        "style": {}
      },
      {
        "type": "range",
        "values": {
          "minValue": "0",
          "maxValue": "10"
        },
        "style": {}
      },
      {
        "type": "string-comparison",
        "values": {
          "string": "test"
        },
        "style": {}
      }
    ],
    "features": {
      "style": {
        "font": "Arial",
        "backgroundColor": "#ff0000"
      },
      "elements": [
        [
          "Release Date",
          {
            "order": "1",
            "style": {
              "color": "#fff000",
              "backgroundColor": "#0fff00"
            }
          }
        ]
      ]
    }
  }
}